{
	"skirmishes": [
		{
			"skirmishName": "Stalingrad-City",
			"swCorner": {
				"xPos": 131000,
				"yPos": 0.0,
				"zPos": 254500
			},
			"neCorner": {
				"xPos": 132000,
				"yPos": 0.0,
				"zPos": 255500
			},
			"startDate": "19420820",
			"stopDate": "19420825",
			"iconicFlightTypes": [
				{
					"side": "AXIS",
					"flightType": "BOMB",
					"maxForcedFlightTypes": 1
				}
			],
			"profileType": "SKIRMISH_PROFILE_CARPET_BOMB",
			"attackerAir": "AXIS",
			"attackerGround": "AXIS"
		}
	]
}