{
  "squadrons": [
    {
      "squadron": -1,
      "date": "19150801"
    },
    {
      "squadron": 302040,
      "date": "19171228"
    },
    {
      "squadron": 302024,
      "date": "19180221"
    },
    {
      "squadron": 302040,
      "date": "19180626"
    },
    {
      "squadron": -6,
      "date": "19180731"
    }
  ],
  "ranks": [
    {
      "rank": 3,
      "date": "19150101"
    },
    {
      "rank": 2,
      "date": "19180301"
    },
    {
      "rank": 1,
      "date": "19180601"
    }
  ],
  "name": "George E H McElroy",
  "serialNumber": 101062,
  "rank": "",
  "picName": "",
  "pilotActiveStatus": 0,
  "country": "BRITAIN",
  "missionFlown": 0,
  "aggressiveness": 0,
  "aiSkillLevel": "ACE",
  "skill": 4,
  "commonSense": 0,
  "skins": [],
  "victories": [
    {
      "date": "19171228",
      "location": "",
      "crashedInSight": false,
      "victim": {
        "airOrGround": 1,
        "name": "",
        "type": "LVG C",
        "squadronName": "",
        "pilotSerialNumber": 0,
        "pilotName": "Unknown",
        "pilotStatus": 0,
        "isGunner": false
      },
      "victor": {
        "airOrGround": 3,
        "name": "",
        "type": "",
        "squadronName": "",
        "pilotSerialNumber": 0,
        "pilotName": "Unknown",
        "pilotStatus": 0,
        "isGunner": false
      }
    },
    {
      "date": "19180113",
      "location": "",
      "crashedInSight": false,
      "victim": {
        "airOrGround": 1,
        "name": "",
        "type": "Rumpler C",
        "squadronName": "",
        "pilotSerialNumber": 0,
        "pilotName": "Unknown",
        "pilotStatus": 0,
        "isGunner": false
      },
      "victor": {
        "airOrGround": 3,
        "name": "",
        "type": "",
        "squadronName": "",
        "pilotSerialNumber": 0,
        "pilotName": "Unknown",
        "pilotStatus": 0,
        "isGunner": false
      }
    },
    {
      "date": "19180119",
      "location": "",
      "crashedInSight": false,
      "victim": {
        "airOrGround": 1,
        "name": "",
        "type": "DFW C",
        "squadronName": "",
        "pilotSerialNumber": 0,
        "pilotName": "Unknown",
        "pilotStatus": 0,
        "isGunner": false
      },
      "victor": {
        "airOrGround": 3,
        "name": "",
        "type": "",
        "squadronName": "",
        "pilotSerialNumber": 0,
        "pilotName": "Unknown",
        "pilotStatus": 0,
        "isGunner": false
      }
    },
    {
      "date": "19180124",
      "location": "",
      "crashedInSight": false,
      "victim": {
        "airOrGround": 1,
        "name": "",
        "type": "DFW C",
        "squadronName": "",
        "pilotSerialNumber": 0,
        "pilotName": "Unknown",
        "pilotStatus": 0,
        "isGunner": false
      },
      "victor": {
        "airOrGround": 3,
        "name": "",
        "type": "",
        "squadronName": "",
        "pilotSerialNumber": 0,
        "pilotName": "Unknown",
        "pilotStatus": 0,
        "isGunner": false
      }
    },
    {
      "date": "19180202",
      "location": "",
      "crashedInSight": false,
      "victim": {
        "airOrGround": 1,
        "name": "",
        "type": "C Type",
        "squadronName": "",
        "pilotSerialNumber": 0,
        "pilotName": "Unknown",
        "pilotStatus": 0,
        "isGunner": false
      },
      "victor": {
        "airOrGround": 3,
        "name": "",
        "type": "",
        "squadronName": "",
        "pilotSerialNumber": 0,
        "pilotName": "Unknown",
        "pilotStatus": 0,
        "isGunner": false
      }
    },
    {
      "date": "19180205",
      "location": "",
      "crashedInSight": false,
      "victim": {
        "airOrGround": 1,
        "name": "",
        "type": "DFW C",
        "squadronName": "",
        "pilotSerialNumber": 0,
        "pilotName": "Unknown",
        "pilotStatus": 0,
        "isGunner": false
      },
      "victor": {
        "airOrGround": 3,
        "name": "",
        "type": "",
        "squadronName": "",
        "pilotSerialNumber": 0,
        "pilotName": "Unknown",
        "pilotStatus": 0,
        "isGunner": false
      }
    },
    {
      "date": "19180205",
      "location": "",
      "crashedInSight": false,
      "victim": {
        "airOrGround": 1,
        "name": "",
        "type": "DFW C",
        "squadronName": "",
        "pilotSerialNumber": 0,
        "pilotName": "Unknown",
        "pilotStatus": 0,
        "isGunner": false
      },
      "victor": {
        "airOrGround": 3,
        "name": "",
        "type": "",
        "squadronName": "",
        "pilotSerialNumber": 0,
        "pilotName": "Unknown",
        "pilotStatus": 0,
        "isGunner": false
      }
    },
    {
      "date": "19180216",
      "location": "",
      "crashedInSight": false,
      "victim": {
        "airOrGround": 1,
        "name": "",
        "type": "DFW C",
        "squadronName": "",
        "pilotSerialNumber": 0,
        "pilotName": "Unknown",
        "pilotStatus": 0,
        "isGunner": false
      },
      "victor": {
        "airOrGround": 3,
        "name": "",
        "type": "",
        "squadronName": "",
        "pilotSerialNumber": 0,
        "pilotName": "Unknown",
        "pilotStatus": 0,
        "isGunner": false
      }
    },
    {
      "date": "19180217",
      "location": "",
      "crashedInSight": false,
      "victim": {
        "airOrGround": 1,
        "name": "",
        "type": "Pfalz D.III",
        "squadronName": "",
        "pilotSerialNumber": 0,
        "pilotName": "Unknown",
        "pilotStatus": 0,
        "isGunner": false
      },
      "victor": {
        "airOrGround": 3,
        "name": "",
        "type": "",
        "squadronName": "",
        "pilotSerialNumber": 0,
        "pilotName": "Unknown",
        "pilotStatus": 0,
        "isGunner": false
      }
    },
    {
      "date": "19180217",
      "location": "",
      "crashedInSight": false,
      "victim": {
        "airOrGround": 1,
        "name": "",
        "type": "C Type",
        "squadronName": "",
        "pilotSerialNumber": 0,
        "pilotName": "Unknown",
        "pilotStatus": 0,
        "isGunner": false
      },
      "victor": {
        "airOrGround": 3,
        "name": "",
        "type": "",
        "squadronName": "",
        "pilotSerialNumber": 0,
        "pilotName": "Unknown",
        "pilotStatus": 0,
        "isGunner": false
      }
    },
    {
      "date": "19180218",
      "location": "",
      "crashedInSight": false,
      "victim": {
        "airOrGround": 1,
        "name": "",
        "type": "Albatros D.V",
        "squadronName": "",
        "pilotSerialNumber": 0,
        "pilotName": "Unknown",
        "pilotStatus": 0,
        "isGunner": false
      },
      "victor": {
        "airOrGround": 3,
        "name": "",
        "type": "",
        "squadronName": "",
        "pilotSerialNumber": 0,
        "pilotName": "Unknown",
        "pilotStatus": 0,
        "isGunner": false
      }
    },
    {
      "date": "19180221",
      "location": "",
      "crashedInSight": false,
      "victim": {
        "airOrGround": 1,
        "name": "",
        "type": "Albatros D.V",
        "squadronName": "",
        "pilotSerialNumber": 0,
        "pilotName": "Unknown",
        "pilotStatus": 0,
        "isGunner": false
      },
      "victor": {
        "airOrGround": 3,
        "name": "",
        "type": "",
        "squadronName": "",
        "pilotSerialNumber": 0,
        "pilotName": "Unknown",
        "pilotStatus": 0,
        "isGunner": false
      }
    },
    {
      "date": "19180226",
      "location": "",
      "crashedInSight": false,
      "victim": {
        "airOrGround": 1,
        "name": "",
        "type": "Fokker DR.I",
        "squadronName": "",
        "pilotSerialNumber": 0,
        "pilotName": "Unknown",
        "pilotStatus": 0,
        "isGunner": false
      },
      "victor": {
        "airOrGround": 3,
        "name": "",
        "type": "",
        "squadronName": "",
        "pilotSerialNumber": 0,
        "pilotName": "Unknown",
        "pilotStatus": 0,
        "isGunner": false
      }
    },
    {
      "date": "19180301",
      "location": "",
      "crashedInSight": false,
      "victim": {
        "airOrGround": 1,
        "name": "",
        "type": "DFW C",
        "squadronName": "",
        "pilotSerialNumber": 0,
        "pilotName": "Unknown",
        "pilotStatus": 0,
        "isGunner": false
      },
      "victor": {
        "airOrGround": 3,
        "name": "",
        "type": "",
        "squadronName": "",
        "pilotSerialNumber": 0,
        "pilotName": "Unknown",
        "pilotStatus": 0,
        "isGunner": false
      }
    },
    {
      "date": "19180306",
      "location": "",
      "crashedInSight": false,
      "victim": {
        "airOrGround": 1,
        "name": "",
        "type": "Albatros D.V",
        "squadronName": "",
        "pilotSerialNumber": 0,
        "pilotName": "Unknown",
        "pilotStatus": 0,
        "isGunner": false
      },
      "victor": {
        "airOrGround": 3,
        "name": "",
        "type": "",
        "squadronName": "",
        "pilotSerialNumber": 0,
        "pilotName": "Unknown",
        "pilotStatus": 0,
        "isGunner": false
      }
    },
    {
      "date": "19180308",
      "location": "",
      "crashedInSight": false,
      "victim": {
        "airOrGround": 1,
        "name": "",
        "type": "DFW C",
        "squadronName": "",
        "pilotSerialNumber": 0,
        "pilotName": "Unknown",
        "pilotStatus": 0,
        "isGunner": false
      },
      "victor": {
        "airOrGround": 3,
        "name": "",
        "type": "",
        "squadronName": "",
        "pilotSerialNumber": 0,
        "pilotName": "Unknown",
        "pilotStatus": 0,
        "isGunner": false
      }
    },
    {
      "date": "19180308",
      "location": "",
      "crashedInSight": false,
      "victim": {
        "airOrGround": 1,
        "name": "",
        "type": "Fokker DR.I",
        "squadronName": "",
        "pilotSerialNumber": 0,
        "pilotName": "Unknown",
        "pilotStatus": 0,
        "isGunner": false
      },
      "victor": {
        "airOrGround": 3,
        "name": "",
        "type": "",
        "squadronName": "",
        "pilotSerialNumber": 0,
        "pilotName": "Unknown",
        "pilotStatus": 0,
        "isGunner": false
      }
    },
    {
      "date": "19180309",
      "location": "",
      "crashedInSight": false,
      "victim": {
        "airOrGround": 1,
        "name": "",
        "type": "Albatros D.V",
        "squadronName": "",
        "pilotSerialNumber": 0,
        "pilotName": "Unknown",
        "pilotStatus": 0,
        "isGunner": false
      },
      "victor": {
        "airOrGround": 3,
        "name": "",
        "type": "",
        "squadronName": "",
        "pilotSerialNumber": 0,
        "pilotName": "Unknown",
        "pilotStatus": 0,
        "isGunner": false
      }
    },
    {
      "date": "19180327",
      "location": "",
      "crashedInSight": false,
      "victim": {
        "airOrGround": 1,
        "name": "",
        "type": "Albatros D.V",
        "squadronName": "",
        "pilotSerialNumber": 0,
        "pilotName": "Unknown",
        "pilotStatus": 0,
        "isGunner": false
      },
      "victor": {
        "airOrGround": 3,
        "name": "",
        "type": "",
        "squadronName": "",
        "pilotSerialNumber": 0,
        "pilotName": "Unknown",
        "pilotStatus": 0,
        "isGunner": false
      }
    },
    {
      "date": "19180329",
      "location": "",
      "crashedInSight": false,
      "victim": {
        "airOrGround": 1,
        "name": "",
        "type": "Albatros D.V",
        "squadronName": "",
        "pilotSerialNumber": 0,
        "pilotName": "Unknown",
        "pilotStatus": 0,
        "isGunner": false
      },
      "victor": {
        "airOrGround": 3,
        "name": "",
        "type": "",
        "squadronName": "",
        "pilotSerialNumber": 0,
        "pilotName": "Unknown",
        "pilotStatus": 0,
        "isGunner": false
      }
    },
    {
      "date": "19180329",
      "location": "",
      "crashedInSight": false,
      "victim": {
        "airOrGround": 1,
        "name": "",
        "type": "DFW C",
        "squadronName": "",
        "pilotSerialNumber": 0,
        "pilotName": "Unknown",
        "pilotStatus": 0,
        "isGunner": false
      },
      "victor": {
        "airOrGround": 3,
        "name": "",
        "type": "",
        "squadronName": "",
        "pilotSerialNumber": 0,
        "pilotName": "Unknown",
        "pilotStatus": 0,
        "isGunner": false
      }
    },
    {
      "date": "19180401",
      "location": "",
      "crashedInSight": false,
      "victim": {
        "airOrGround": 1,
        "name": "",
        "type": "Albatros D.V",
        "squadronName": "",
        "pilotSerialNumber": 0,
        "pilotName": "Unknown",
        "pilotStatus": 0,
        "isGunner": false
      },
      "victor": {
        "airOrGround": 3,
        "name": "",
        "type": "",
        "squadronName": "",
        "pilotSerialNumber": 0,
        "pilotName": "Unknown",
        "pilotStatus": 0,
        "isGunner": false
      }
    },
    {
      "date": "19180402",
      "location": "",
      "crashedInSight": false,
      "victim": {
        "airOrGround": 1,
        "name": "",
        "type": "Albatros D.V",
        "squadronName": "",
        "pilotSerialNumber": 0,
        "pilotName": "Unknown",
        "pilotStatus": 0,
        "isGunner": false
      },
      "victor": {
        "airOrGround": 3,
        "name": "",
        "type": "",
        "squadronName": "",
        "pilotSerialNumber": 0,
        "pilotName": "Unknown",
        "pilotStatus": 0,
        "isGunner": false
      }
    },
    {
      "date": "19180404",
      "location": "",
      "crashedInSight": false,
      "victim": {
        "airOrGround": 1,
        "name": "",
        "type": "Pfalz D.III",
        "squadronName": "",
        "pilotSerialNumber": 0,
        "pilotName": "Unknown",
        "pilotStatus": 0,
        "isGunner": false
      },
      "victor": {
        "airOrGround": 3,
        "name": "",
        "type": "",
        "squadronName": "",
        "pilotSerialNumber": 0,
        "pilotName": "Unknown",
        "pilotStatus": 0,
        "isGunner": false
      }
    },
    {
      "date": "19180407",
      "location": "",
      "crashedInSight": false,
      "victim": {
        "airOrGround": 1,
        "name": "",
        "type": "Albatros D.V",
        "squadronName": "",
        "pilotSerialNumber": 0,
        "pilotName": "Unknown",
        "pilotStatus": 0,
        "isGunner": false
      },
      "victor": {
        "airOrGround": 3,
        "name": "",
        "type": "",
        "squadronName": "",
        "pilotSerialNumber": 0,
        "pilotName": "Unknown",
        "pilotStatus": 0,
        "isGunner": false
      }
    },
    {
      "date": "19180407",
      "location": "",
      "crashedInSight": false,
      "victim": {
        "airOrGround": 1,
        "name": "",
        "type": "Albatros D.V",
        "squadronName": "",
        "pilotSerialNumber": 0,
        "pilotName": "Unknown",
        "pilotStatus": 0,
        "isGunner": false
      },
      "victor": {
        "airOrGround": 3,
        "name": "",
        "type": "",
        "squadronName": "",
        "pilotSerialNumber": 0,
        "pilotName": "Unknown",
        "pilotStatus": 0,
        "isGunner": false
      }
    },
    {
      "date": "19180407",
      "location": "",
      "crashedInSight": false,
      "victim": {
        "airOrGround": 1,
        "name": "",
        "type": "Fokker DR.I",
        "squadronName": "",
        "pilotSerialNumber": 0,
        "pilotName": "Unknown",
        "pilotStatus": 0,
        "isGunner": false
      },
      "victor": {
        "airOrGround": 3,
        "name": "",
        "type": "",
        "squadronName": "",
        "pilotSerialNumber": 0,
        "pilotName": "Unknown",
        "pilotStatus": 0,
        "isGunner": false
      }
    },
    {
      "date": "19180626",
      "location": "",
      "crashedInSight": false,
      "victim": {
        "airOrGround": 1,
        "name": "",
        "type": "DFW C",
        "squadronName": "",
        "pilotSerialNumber": 0,
        "pilotName": "Unknown",
        "pilotStatus": 0,
        "isGunner": false
      },
      "victor": {
        "airOrGround": 3,
        "name": "",
        "type": "",
        "squadronName": "",
        "pilotSerialNumber": 0,
        "pilotName": "Unknown",
        "pilotStatus": 0,
        "isGunner": false
      }
    },
    {
      "date": "19180628",
      "location": "",
      "crashedInSight": false,
      "victim": {
        "airOrGround": 1,
        "name": "",
        "type": "Balloon",
        "squadronName": "",
        "pilotSerialNumber": 0,
        "pilotName": "Unknown",
        "pilotStatus": 0,
        "isGunner": false
      },
      "victor": {
        "airOrGround": 3,
        "name": "",
        "type": "",
        "squadronName": "",
        "pilotSerialNumber": 0,
        "pilotName": "Unknown",
        "pilotStatus": 0,
        "isGunner": false
      }
    },
    {
      "date": "19180630",
      "location": "",
      "crashedInSight": false,
      "victim": {
        "airOrGround": 1,
        "name": "",
        "type": "Balloon",
        "squadronName": "",
        "pilotSerialNumber": 0,
        "pilotName": "Unknown",
        "pilotStatus": 0,
        "isGunner": false
      },
      "victor": {
        "airOrGround": 3,
        "name": "",
        "type": "",
        "squadronName": "",
        "pilotSerialNumber": 0,
        "pilotName": "Unknown",
        "pilotStatus": 0,
        "isGunner": false
      }
    },
    {
      "date": "19180701",
      "location": "",
      "crashedInSight": false,
      "victim": {
        "airOrGround": 1,
        "name": "",
        "type": "Balloon",
        "squadronName": "",
        "pilotSerialNumber": 0,
        "pilotName": "Unknown",
        "pilotStatus": 0,
        "isGunner": false
      },
      "victor": {
        "airOrGround": 3,
        "name": "",
        "type": "",
        "squadronName": "",
        "pilotSerialNumber": 0,
        "pilotName": "Unknown",
        "pilotStatus": 0,
        "isGunner": false
      }
    },
    {
      "date": "19180702",
      "location": "",
      "crashedInSight": false,
      "victim": {
        "airOrGround": 1,
        "name": "",
        "type": "DFW C",
        "squadronName": "",
        "pilotSerialNumber": 0,
        "pilotName": "Unknown",
        "pilotStatus": 0,
        "isGunner": false
      },
      "victor": {
        "airOrGround": 3,
        "name": "",
        "type": "",
        "squadronName": "",
        "pilotSerialNumber": 0,
        "pilotName": "Unknown",
        "pilotStatus": 0,
        "isGunner": false
      }
    },
    {
      "date": "19180702",
      "location": "",
      "crashedInSight": false,
      "victim": {
        "airOrGround": 1,
        "name": "",
        "type": "DFW C",
        "squadronName": "",
        "pilotSerialNumber": 0,
        "pilotName": "Unknown",
        "pilotStatus": 0,
        "isGunner": false
      },
      "victor": {
        "airOrGround": 3,
        "name": "",
        "type": "",
        "squadronName": "",
        "pilotSerialNumber": 0,
        "pilotName": "Unknown",
        "pilotStatus": 0,
        "isGunner": false
      }
    },
    {
      "date": "19180705",
      "location": "",
      "crashedInSight": false,
      "victim": {
        "airOrGround": 1,
        "name": "",
        "type": "DFW C",
        "squadronName": "",
        "pilotSerialNumber": 0,
        "pilotName": "Unknown",
        "pilotStatus": 0,
        "isGunner": false
      },
      "victor": {
        "airOrGround": 3,
        "name": "",
        "type": "",
        "squadronName": "",
        "pilotSerialNumber": 0,
        "pilotName": "Unknown",
        "pilotStatus": 0,
        "isGunner": false
      }
    },
    {
      "date": "19180706",
      "location": "",
      "crashedInSight": false,
      "victim": {
        "airOrGround": 1,
        "name": "",
        "type": "Hannover C",
        "squadronName": "",
        "pilotSerialNumber": 0,
        "pilotName": "Unknown",
        "pilotStatus": 0,
        "isGunner": false
      },
      "victor": {
        "airOrGround": 3,
        "name": "",
        "type": "",
        "squadronName": "",
        "pilotSerialNumber": 0,
        "pilotName": "Unknown",
        "pilotStatus": 0,
        "isGunner": false
      }
    },
    {
      "date": "19180708",
      "location": "",
      "crashedInSight": false,
      "victim": {
        "airOrGround": 1,
        "name": "",
        "type": "Hannover C",
        "squadronName": "",
        "pilotSerialNumber": 0,
        "pilotName": "Unknown",
        "pilotStatus": 0,
        "isGunner": false
      },
      "victor": {
        "airOrGround": 3,
        "name": "",
        "type": "",
        "squadronName": "",
        "pilotSerialNumber": 0,
        "pilotName": "Unknown",
        "pilotStatus": 0,
        "isGunner": false
      }
    },
    {
      "date": "19180708",
      "location": "",
      "crashedInSight": false,
      "victim": {
        "airOrGround": 1,
        "name": "",
        "type": "Hannover C",
        "squadronName": "",
        "pilotSerialNumber": 0,
        "pilotName": "Unknown",
        "pilotStatus": 0,
        "isGunner": false
      },
      "victor": {
        "airOrGround": 3,
        "name": "",
        "type": "",
        "squadronName": "",
        "pilotSerialNumber": 0,
        "pilotName": "Unknown",
        "pilotStatus": 0,
        "isGunner": false
      }
    },
    {
      "date": "19180711",
      "location": "",
      "crashedInSight": false,
      "victim": {
        "airOrGround": 1,
        "name": "",
        "type": "Hannover C",
        "squadronName": "",
        "pilotSerialNumber": 0,
        "pilotName": "Unknown",
        "pilotStatus": 0,
        "isGunner": false
      },
      "victor": {
        "airOrGround": 3,
        "name": "",
        "type": "",
        "squadronName": "",
        "pilotSerialNumber": 0,
        "pilotName": "Unknown",
        "pilotStatus": 0,
        "isGunner": false
      }
    },
    {
      "date": "19180713",
      "location": "",
      "crashedInSight": false,
      "victim": {
        "airOrGround": 1,
        "name": "",
        "type": "Hannover C",
        "squadronName": "",
        "pilotSerialNumber": 0,
        "pilotName": "Unknown",
        "pilotStatus": 0,
        "isGunner": false
      },
      "victor": {
        "airOrGround": 3,
        "name": "",
        "type": "",
        "squadronName": "",
        "pilotSerialNumber": 0,
        "pilotName": "Unknown",
        "pilotStatus": 0,
        "isGunner": false
      }
    },
    {
      "date": "19180713",
      "location": "",
      "crashedInSight": false,
      "victim": {
        "airOrGround": 1,
        "name": "",
        "type": "Pfalz D.III",
        "squadronName": "",
        "pilotSerialNumber": 0,
        "pilotName": "Unknown",
        "pilotStatus": 0,
        "isGunner": false
      },
      "victor": {
        "airOrGround": 3,
        "name": "",
        "type": "",
        "squadronName": "",
        "pilotSerialNumber": 0,
        "pilotName": "Unknown",
        "pilotStatus": 0,
        "isGunner": false
      }
    },
    {
      "date": "19180714",
      "location": "",
      "crashedInSight": false,
      "victim": {
        "airOrGround": 1,
        "name": "",
        "type": "Hannover C",
        "squadronName": "",
        "pilotSerialNumber": 0,
        "pilotName": "Unknown",
        "pilotStatus": 0,
        "isGunner": false
      },
      "victor": {
        "airOrGround": 3,
        "name": "",
        "type": "",
        "squadronName": "",
        "pilotSerialNumber": 0,
        "pilotName": "Unknown",
        "pilotStatus": 0,
        "isGunner": false
      }
    },
    {
      "date": "19180715",
      "location": "",
      "crashedInSight": false,
      "victim": {
        "airOrGround": 1,
        "name": "",
        "type": "Fokker D.VII",
        "squadronName": "",
        "pilotSerialNumber": 0,
        "pilotName": "Unknown",
        "pilotStatus": 0,
        "isGunner": false
      },
      "victor": {
        "airOrGround": 3,
        "name": "",
        "type": "",
        "squadronName": "",
        "pilotSerialNumber": 0,
        "pilotName": "Unknown",
        "pilotStatus": 0,
        "isGunner": false
      }
    },
    {
      "date": "19180715",
      "location": "",
      "crashedInSight": false,
      "victim": {
        "airOrGround": 1,
        "name": "",
        "type": "Fokker D.VII",
        "squadronName": "",
        "pilotSerialNumber": 0,
        "pilotName": "Unknown",
        "pilotStatus": 0,
        "isGunner": false
      },
      "victor": {
        "airOrGround": 3,
        "name": "",
        "type": "",
        "squadronName": "",
        "pilotSerialNumber": 0,
        "pilotName": "Unknown",
        "pilotStatus": 0,
        "isGunner": false
      }
    },
    {
      "date": "19180719",
      "location": "",
      "crashedInSight": false,
      "victim": {
        "airOrGround": 1,
        "name": "",
        "type": "Albatros D.V",
        "squadronName": "",
        "pilotSerialNumber": 0,
        "pilotName": "Unknown",
        "pilotStatus": 0,
        "isGunner": false
      },
      "victor": {
        "airOrGround": 3,
        "name": "",
        "type": "",
        "squadronName": "",
        "pilotSerialNumber": 0,
        "pilotName": "Unknown",
        "pilotStatus": 0,
        "isGunner": false
      }
    },
    {
      "date": "19180725",
      "location": "",
      "crashedInSight": false,
      "victim": {
        "airOrGround": 1,
        "name": "",
        "type": "Hannover C",
        "squadronName": "",
        "pilotSerialNumber": 0,
        "pilotName": "Unknown",
        "pilotStatus": 0,
        "isGunner": false
      },
      "victor": {
        "airOrGround": 3,
        "name": "",
        "type": "",
        "squadronName": "",
        "pilotSerialNumber": 0,
        "pilotName": "Unknown",
        "pilotStatus": 0,
        "isGunner": false
      }
    },
    {
      "date": "19180725",
      "location": "",
      "crashedInSight": false,
      "victim": {
        "airOrGround": 1,
        "name": "",
        "type": "Hannover C",
        "squadronName": "",
        "pilotSerialNumber": 0,
        "pilotName": "Unknown",
        "pilotStatus": 0,
        "isGunner": false
      },
      "victor": {
        "airOrGround": 3,
        "name": "",
        "type": "",
        "squadronName": "",
        "pilotSerialNumber": 0,
        "pilotName": "Unknown",
        "pilotStatus": 0,
        "isGunner": false
      }
    },
    {
      "date": "19180731",
      "location": "",
      "crashedInSight": false,
      "victim": {
        "airOrGround": 1,
        "name": "",
        "type": "Hannover C",
        "squadronName": "",
        "pilotSerialNumber": 0,
        "pilotName": "Unknown",
        "pilotStatus": 0,
        "isGunner": false
      },
      "victor": {
        "airOrGround": 3,
        "name": "",
        "type": "",
        "squadronName": "",
        "pilotSerialNumber": 0,
        "pilotName": "Unknown",
        "pilotStatus": 0,
        "isGunner": false
      }
    }
  ],
  "groundVictories": [],
  "medals": [
    {
      "medalDate": "19180124",
      "medalName": "Distinguished Flying Cross",
      "medalImage": ""
    },
    {
      "medalDate": "19180217",
      "medalName": "Distinguished Flying Cross With Bar",
      "medalImage": ""
    },
    {
      "medalDate": "19180628",
      "medalName": "Military Cross",
      "medalImage": ""
    }
  ],
  "playerRegion": "",
  "squadronId": -1
}