{
  "squadrons": [
    {
      "squadron": -1,
      "date": "19150801"
    },
    {
      "squadron": 302210,
      "date": "19170602"
    },
    {
      "squadron": -1,
      "date": "19180603"
    },
    {
      "squadron": -6,
      "date": "19181201"
    }
  ],
  "ranks": [
    {
      "rank": 3,
      "date": "19150101"
    },
    {
      "rank": 2,
      "date": "19170801"
    },
    {
      "rank": 1,
      "date": "19180301"
    }
  ],
  "name": "William Alexander",
  "serialNumber": 101177,
  "rank": "",
  "picName": "",
  "pilotActiveStatus": 0,
  "country": "BRITAIN",
  "missionFlown": 0,
  "aggressiveness": 0,
  "aiSkillLevel": "ACE",
  "skill": 4,
  "commonSense": 0,
  "skins": [],
  "victories": [
    {
      "date": "19170602",
      "location": "",
      "crashedInSight": false,
      "victim": {
        "airOrGround": 1,
        "name": "",
        "type": "C Type",
        "squadronName": "",
        "pilotSerialNumber": 0,
        "pilotName": "Unknown",
        "pilotStatus": 0,
        "isGunner": false
      },
      "victor": {
        "airOrGround": 3,
        "name": "",
        "type": "",
        "squadronName": "",
        "pilotSerialNumber": 0,
        "pilotName": "Unknown",
        "pilotStatus": 0,
        "isGunner": false
      }
    },
    {
      "date": "19170604",
      "location": "",
      "crashedInSight": false,
      "victim": {
        "airOrGround": 1,
        "name": "",
        "type": "Albatros D.III",
        "squadronName": "",
        "pilotSerialNumber": 0,
        "pilotName": "Unknown",
        "pilotStatus": 0,
        "isGunner": false
      },
      "victor": {
        "airOrGround": 3,
        "name": "",
        "type": "",
        "squadronName": "",
        "pilotSerialNumber": 0,
        "pilotName": "Unknown",
        "pilotStatus": 0,
        "isGunner": false
      }
    },
    {
      "date": "19170606",
      "location": "",
      "crashedInSight": false,
      "victim": {
        "airOrGround": 1,
        "name": "",
        "type": "Albatros D.III",
        "squadronName": "",
        "pilotSerialNumber": 0,
        "pilotName": "Unknown",
        "pilotStatus": 0,
        "isGunner": false
      },
      "victor": {
        "airOrGround": 3,
        "name": "",
        "type": "",
        "squadronName": "",
        "pilotSerialNumber": 0,
        "pilotName": "Unknown",
        "pilotStatus": 0,
        "isGunner": false
      }
    },
    {
      "date": "19170706",
      "location": "",
      "crashedInSight": false,
      "victim": {
        "airOrGround": 1,
        "name": "",
        "type": "Albatros D.III",
        "squadronName": "",
        "pilotSerialNumber": 0,
        "pilotName": "Unknown",
        "pilotStatus": 0,
        "isGunner": false
      },
      "victor": {
        "airOrGround": 3,
        "name": "",
        "type": "",
        "squadronName": "",
        "pilotSerialNumber": 0,
        "pilotName": "Unknown",
        "pilotStatus": 0,
        "isGunner": false
      }
    },
    {
      "date": "19170706",
      "location": "",
      "crashedInSight": false,
      "victim": {
        "airOrGround": 1,
        "name": "",
        "type": "Albatros D.III",
        "squadronName": "",
        "pilotSerialNumber": 0,
        "pilotName": "Unknown",
        "pilotStatus": 0,
        "isGunner": false
      },
      "victor": {
        "airOrGround": 3,
        "name": "",
        "type": "",
        "squadronName": "",
        "pilotSerialNumber": 0,
        "pilotName": "Unknown",
        "pilotStatus": 0,
        "isGunner": false
      }
    },
    {
      "date": "19170711",
      "location": "",
      "crashedInSight": false,
      "victim": {
        "airOrGround": 1,
        "name": "",
        "type": "Albatros D.V",
        "squadronName": "",
        "pilotSerialNumber": 0,
        "pilotName": "Unknown",
        "pilotStatus": 0,
        "isGunner": false
      },
      "victor": {
        "airOrGround": 3,
        "name": "",
        "type": "",
        "squadronName": "",
        "pilotSerialNumber": 0,
        "pilotName": "Unknown",
        "pilotStatus": 0,
        "isGunner": false
      }
    },
    {
      "date": "19170720",
      "location": "",
      "crashedInSight": false,
      "victim": {
        "airOrGround": 1,
        "name": "",
        "type": "Albatros D.V",
        "squadronName": "",
        "pilotSerialNumber": 0,
        "pilotName": "Unknown",
        "pilotStatus": 0,
        "isGunner": false
      },
      "victor": {
        "airOrGround": 3,
        "name": "",
        "type": "",
        "squadronName": "",
        "pilotSerialNumber": 0,
        "pilotName": "Unknown",
        "pilotStatus": 0,
        "isGunner": false
      }
    },
    {
      "date": "19170728",
      "location": "",
      "crashedInSight": false,
      "victim": {
        "airOrGround": 1,
        "name": "",
        "type": "Albatros D.V",
        "squadronName": "",
        "pilotSerialNumber": 0,
        "pilotName": "Unknown",
        "pilotStatus": 0,
        "isGunner": false
      },
      "victor": {
        "airOrGround": 3,
        "name": "",
        "type": "",
        "squadronName": "",
        "pilotSerialNumber": 0,
        "pilotName": "Unknown",
        "pilotStatus": 0,
        "isGunner": false
      }
    },
    {
      "date": "19170816",
      "location": "",
      "crashedInSight": false,
      "victim": {
        "airOrGround": 1,
        "name": "",
        "type": "Albatros D.V",
        "squadronName": "",
        "pilotSerialNumber": 0,
        "pilotName": "Unknown",
        "pilotStatus": 0,
        "isGunner": false
      },
      "victor": {
        "airOrGround": 3,
        "name": "",
        "type": "",
        "squadronName": "",
        "pilotSerialNumber": 0,
        "pilotName": "Unknown",
        "pilotStatus": 0,
        "isGunner": false
      }
    },
    {
      "date": "19170820",
      "location": "",
      "crashedInSight": false,
      "victim": {
        "airOrGround": 1,
        "name": "",
        "type": "Albatros D.V",
        "squadronName": "",
        "pilotSerialNumber": 0,
        "pilotName": "Unknown",
        "pilotStatus": 0,
        "isGunner": false
      },
      "victor": {
        "airOrGround": 3,
        "name": "",
        "type": "",
        "squadronName": "",
        "pilotSerialNumber": 0,
        "pilotName": "Unknown",
        "pilotStatus": 0,
        "isGunner": false
      }
    },
    {
      "date": "19170821",
      "location": "",
      "crashedInSight": false,
      "victim": {
        "airOrGround": 1,
        "name": "",
        "type": "Albatros D.V",
        "squadronName": "",
        "pilotSerialNumber": 0,
        "pilotName": "Unknown",
        "pilotStatus": 0,
        "isGunner": false
      },
      "victor": {
        "airOrGround": 3,
        "name": "",
        "type": "",
        "squadronName": "",
        "pilotSerialNumber": 0,
        "pilotName": "Unknown",
        "pilotStatus": 0,
        "isGunner": false
      }
    },
    {
      "date": "19170923",
      "location": "",
      "crashedInSight": false,
      "victim": {
        "airOrGround": 1,
        "name": "",
        "type": "Albatros D.V",
        "squadronName": "",
        "pilotSerialNumber": 0,
        "pilotName": "Unknown",
        "pilotStatus": 0,
        "isGunner": false
      },
      "victor": {
        "airOrGround": 3,
        "name": "",
        "type": "",
        "squadronName": "",
        "pilotSerialNumber": 0,
        "pilotName": "Unknown",
        "pilotStatus": 0,
        "isGunner": false
      }
    },
    {
      "date": "19180123",
      "location": "",
      "crashedInSight": false,
      "victim": {
        "airOrGround": 1,
        "name": "",
        "type": "Albatros D.V",
        "squadronName": "",
        "pilotSerialNumber": 0,
        "pilotName": "Unknown",
        "pilotStatus": 0,
        "isGunner": false
      },
      "victor": {
        "airOrGround": 3,
        "name": "",
        "type": "",
        "squadronName": "",
        "pilotSerialNumber": 0,
        "pilotName": "Unknown",
        "pilotStatus": 0,
        "isGunner": false
      }
    },
    {
      "date": "19180306",
      "location": "",
      "crashedInSight": false,
      "victim": {
        "airOrGround": 1,
        "name": "",
        "type": "Albatros D.V",
        "squadronName": "",
        "pilotSerialNumber": 0,
        "pilotName": "Unknown",
        "pilotStatus": 0,
        "isGunner": false
      },
      "victor": {
        "airOrGround": 3,
        "name": "",
        "type": "",
        "squadronName": "",
        "pilotSerialNumber": 0,
        "pilotName": "Unknown",
        "pilotStatus": 0,
        "isGunner": false
      }
    },
    {
      "date": "19180310",
      "location": "",
      "crashedInSight": false,
      "victim": {
        "airOrGround": 1,
        "name": "",
        "type": "C Type",
        "squadronName": "",
        "pilotSerialNumber": 0,
        "pilotName": "Unknown",
        "pilotStatus": 0,
        "isGunner": false
      },
      "victor": {
        "airOrGround": 3,
        "name": "",
        "type": "",
        "squadronName": "",
        "pilotSerialNumber": 0,
        "pilotName": "Unknown",
        "pilotStatus": 0,
        "isGunner": false
      }
    },
    {
      "date": "19180324",
      "location": "",
      "crashedInSight": false,
      "victim": {
        "airOrGround": 1,
        "name": "",
        "type": "Albatros D.V",
        "squadronName": "",
        "pilotSerialNumber": 0,
        "pilotName": "Unknown",
        "pilotStatus": 0,
        "isGunner": false
      },
      "victor": {
        "airOrGround": 3,
        "name": "",
        "type": "",
        "squadronName": "",
        "pilotSerialNumber": 0,
        "pilotName": "Unknown",
        "pilotStatus": 0,
        "isGunner": false
      }
    },
    {
      "date": "19180324",
      "location": "",
      "crashedInSight": false,
      "victim": {
        "airOrGround": 1,
        "name": "",
        "type": "Albatros D.V",
        "squadronName": "",
        "pilotSerialNumber": 0,
        "pilotName": "Unknown",
        "pilotStatus": 0,
        "isGunner": false
      },
      "victor": {
        "airOrGround": 3,
        "name": "",
        "type": "",
        "squadronName": "",
        "pilotSerialNumber": 0,
        "pilotName": "Unknown",
        "pilotStatus": 0,
        "isGunner": false
      }
    },
    {
      "date": "19180403",
      "location": "",
      "crashedInSight": false,
      "victim": {
        "airOrGround": 1,
        "name": "",
        "type": "C Type",
        "squadronName": "",
        "pilotSerialNumber": 0,
        "pilotName": "Unknown",
        "pilotStatus": 0,
        "isGunner": false
      },
      "victor": {
        "airOrGround": 3,
        "name": "",
        "type": "",
        "squadronName": "",
        "pilotSerialNumber": 0,
        "pilotName": "Unknown",
        "pilotStatus": 0,
        "isGunner": false
      }
    },
    {
      "date": "19180411",
      "location": "",
      "crashedInSight": false,
      "victim": {
        "airOrGround": 1,
        "name": "",
        "type": "C Type",
        "squadronName": "",
        "pilotSerialNumber": 0,
        "pilotName": "Unknown",
        "pilotStatus": 0,
        "isGunner": false
      },
      "victor": {
        "airOrGround": 3,
        "name": "",
        "type": "",
        "squadronName": "",
        "pilotSerialNumber": 0,
        "pilotName": "Unknown",
        "pilotStatus": 0,
        "isGunner": false
      }
    },
    {
      "date": "19180511",
      "location": "",
      "crashedInSight": false,
      "victim": {
        "airOrGround": 1,
        "name": "",
        "type": "Albatros D.V",
        "squadronName": "",
        "pilotSerialNumber": 0,
        "pilotName": "Unknown",
        "pilotStatus": 0,
        "isGunner": false
      },
      "victor": {
        "airOrGround": 3,
        "name": "",
        "type": "",
        "squadronName": "",
        "pilotSerialNumber": 0,
        "pilotName": "Unknown",
        "pilotStatus": 0,
        "isGunner": false
      }
    },
    {
      "date": "19180518",
      "location": "",
      "crashedInSight": false,
      "victim": {
        "airOrGround": 1,
        "name": "",
        "type": "Pfalz D.III",
        "squadronName": "",
        "pilotSerialNumber": 0,
        "pilotName": "Unknown",
        "pilotStatus": 0,
        "isGunner": false
      },
      "victor": {
        "airOrGround": 3,
        "name": "",
        "type": "",
        "squadronName": "",
        "pilotSerialNumber": 0,
        "pilotName": "Unknown",
        "pilotStatus": 0,
        "isGunner": false
      }
    },
    {
      "date": "19180527",
      "location": "",
      "crashedInSight": false,
      "victim": {
        "airOrGround": 1,
        "name": "",
        "type": "Pfalz D.III",
        "squadronName": "",
        "pilotSerialNumber": 0,
        "pilotName": "Unknown",
        "pilotStatus": 0,
        "isGunner": false
      },
      "victor": {
        "airOrGround": 3,
        "name": "",
        "type": "",
        "squadronName": "",
        "pilotSerialNumber": 0,
        "pilotName": "Unknown",
        "pilotStatus": 0,
        "isGunner": false
      }
    }
  ],
  "groundVictories": [],
  "medals": [
    {
      "medalDate": "19170706",
      "medalName": "Distinguished Service Cross",
      "medalImage": ""
    }
  ],
  "playerRegion": "",
  "squadronId": -1
}